SpringShizhanZhongwenDiliubanMeapFix1/README.md
SpringShizhanZhongwenDiliubanMeapFix1/__init__.py
SpringShizhanZhongwenDiliubanMeapFix1/__main__.py
SpringShizhanZhongwenDiliubanMeapFix1/file.epub
SpringShizhanZhongwenDiliubanMeapFix1/index.html
SpringShizhanZhongwenDiliubanMeapFix1/css/__init__.py
SpringShizhanZhongwenDiliubanMeapFix1/css/annotations.css
SpringShizhanZhongwenDiliubanMeapFix1/css/main.css
SpringShizhanZhongwenDiliubanMeapFix1/css/normalize.css
SpringShizhanZhongwenDiliubanMeapFix1/css/popup.css
SpringShizhanZhongwenDiliubanMeapFix1/font/__init__.py
SpringShizhanZhongwenDiliubanMeapFix1/font/fontello.eot
SpringShizhanZhongwenDiliubanMeapFix1/font/fontello.svg
SpringShizhanZhongwenDiliubanMeapFix1/font/fontello.ttf
SpringShizhanZhongwenDiliubanMeapFix1/font/fontello.woff
SpringShizhanZhongwenDiliubanMeapFix1/img/__init__.py
SpringShizhanZhongwenDiliubanMeapFix1/img/annotator-glyph-sprite.png
SpringShizhanZhongwenDiliubanMeapFix1/img/annotator-icon-sprite.png
SpringShizhanZhongwenDiliubanMeapFix1/img/apple-touch-icon.png
SpringShizhanZhongwenDiliubanMeapFix1/img/cancelfullscreen.png
SpringShizhanZhongwenDiliubanMeapFix1/img/close.png
SpringShizhanZhongwenDiliubanMeapFix1/img/fullscreen.png
SpringShizhanZhongwenDiliubanMeapFix1/img/loader.gif
SpringShizhanZhongwenDiliubanMeapFix1/img/menu-icon.png
SpringShizhanZhongwenDiliubanMeapFix1/img/save.png
SpringShizhanZhongwenDiliubanMeapFix1/img/saved.png
SpringShizhanZhongwenDiliubanMeapFix1/img/settings-s.png
SpringShizhanZhongwenDiliubanMeapFix1/img/settings.png
SpringShizhanZhongwenDiliubanMeapFix1/img/star.png
SpringShizhanZhongwenDiliubanMeapFix1/js/__init__.py
SpringShizhanZhongwenDiliubanMeapFix1/js/epub.js
SpringShizhanZhongwenDiliubanMeapFix1/js/epub.min.js
SpringShizhanZhongwenDiliubanMeapFix1/js/epub.min.map
SpringShizhanZhongwenDiliubanMeapFix1/js/hooks.min.js
SpringShizhanZhongwenDiliubanMeapFix1/js/hooks.min.map
SpringShizhanZhongwenDiliubanMeapFix1/js/reader.js
spring_shizhan_zhongwen_diliuban_meap_fix1-2025.3.25.1.dist-info/METADATA
spring_shizhan_zhongwen_diliuban_meap_fix1-2025.3.25.1.dist-info/WHEEL
spring_shizhan_zhongwen_diliuban_meap_fix1-2025.3.25.1.dist-info/entry_points.txt
spring_shizhan_zhongwen_diliuban_meap_fix1-2025.3.25.1.dist-info/top_level.txt
spring_shizhan_zhongwen_diliuban_meap_fix1-2025.3.25.1.dist-info/RECORD
